AUTHORS.rst
CONTRIBUTING.rst
HISTORY.rst
LICENSE
MANIFEST.in
README.rst
setup.cfg
setup.py
docs/Makefile
docs/authors.rst
docs/conf.py
docs/contributing.rst
docs/history.rst
docs/index.rst
docs/installation.rst
docs/make.bat
docs/readme.rst
docs/usage.rst
sing/__init__.py
sing/sing.py
sing.egg-info/PKG-INFO
sing.egg-info/SOURCES.txt
sing.egg-info/dependency_links.txt
sing.egg-info/not-zip-safe
sing.egg-info/requires.txt
sing.egg-info/top_level.txt
tests/test_sing.py