Metadata-Version: 1.1
Name: sing
Version: 0.1.1
Summary: Ensure a single process is running. Using lockfile and process checking.
Home-page: https://github.com/dariosky/python-sing
Author: Dario Varotto
Author-email: dario.varotto@gmail.com
License: MIT license
Keywords: sing
Platform: UNKNOWN
Classifier: Development Status :: 2 - Pre-Alpha
Classifier: Intended Audience :: Developers
Classifier: License :: OSI Approved :: MIT License
Classifier: Natural Language :: English
Classifier: Programming Language :: Python :: 2
Classifier: Programming Language :: Python :: 2.7
Classifier: Programming Language :: Python :: 3
Classifier: Programming Language :: Python :: 3.4
Classifier: Programming Language :: Python :: 3.5
Classifier: Programming Language :: Python :: 3.6
